nld/__init__.py
nld/nld.py
nld/utils.py
nld-0.0.1.dist-info/LICENSE
nld-0.0.1.dist-info/METADATA
nld-0.0.1.dist-info/WHEEL
nld-0.0.1.dist-info/top_level.txt
nld-0.0.1.dist-info/RECORD
