Metadata-Version: 2.1
Name: nld
Version: 0.0.1
Summary: A small package that provides decorators for text preprocessing with nltk
Home-page: https://github.com/andcarnivorous/nld
Author: Andrea Favia
Author-email: drewlinguistics01@gmail.com
License: UNKNOWN
Platform: UNKNOWN
Classifier: Programming Language :: Python :: 3
Classifier: License :: OSI Approved :: MIT License
Classifier: Operating System :: OS Independent
Requires-Python: >=3.6
Requires-Dist: nltk (==3.4.5)
Requires-Dist: pandas (>=0.25.3)
Requires-Dist: numpy (==1.19.0)
